README.md
setup.py
obj2stl/__init__.py
obj2stl/camera.py
obj2stl/controls.py
obj2stl/geometry.py
obj2stl/obj2stl.py
obj2stl/shader.py
obj2stl.egg-info/PKG-INFO
obj2stl.egg-info/SOURCES.txt
obj2stl.egg-info/dependency_links.txt
obj2stl.egg-info/requires.txt
obj2stl.egg-info/top_level.txt
obj2stl/model/__init__.py
obj2stl/model/basemodel.py
obj2stl/model/mesh.py
obj2stl/model/tools.py
obj2stl/model/formats/__init__.py
obj2stl/model/formats/obj.py
obj2stl/model/formats/off.py
obj2stl/model/formats/ply.py
obj2stl/model/formats/stl.py