Metadata-Version: 2.1
Name: obj2stl
Version: 4.0.1
Summary: simple and lightweight 3D model format converter from obj to stl
Home-page: https://github.com/you/your_package
Author: Abdullah Alzaidy
Author-email: alzaidy.abdullah@gmail.com
License: Apache License 2.0
Platform: UNKNOWN
